govtech_csg_xcg/viewpermissions/__init__.py
govtech_csg_xcg/viewpermissions/apps.py
govtech_csg_xcg/viewpermissions/decorators.py
govtech_csg_xcg/viewpermissions/middleware.py
govtech_csg_xcg/viewpermissions/patch/__init__.py
govtech_csg_xcg/viewpermissions/patch/patch.py
govtech_csg_xcg/viewpermissions/patch/permission.py
govtech_csg_xcg_viewpermissions-0.1.0.dist-info/LICENSE
govtech_csg_xcg_viewpermissions-0.1.0.dist-info/METADATA
govtech_csg_xcg_viewpermissions-0.1.0.dist-info/WHEEL
govtech_csg_xcg_viewpermissions-0.1.0.dist-info/top_level.txt
govtech_csg_xcg_viewpermissions-0.1.0.dist-info/RECORD
