Metadata-Version: 2.1
Name: govtech-csg-xcg-viewpermissions
Version: 0.1.0
Summary: XCG security middleware for Django to mandate explicit authorization checks.
Project-URL: Homepage, https://xcg.tech.gov.sg
Project-URL: Documentation, https://xcg.tech.gov.sg
Project-URL: Repository, https://github.com/GovTech-CSG/govtech-csg-xcg-viewpermissions
Classifier: Development Status :: 4 - Beta
Classifier: License :: OSI Approved :: Mozilla Public License 2.0 (MPL 2.0)
Requires-Python: >=3.8
License-File: LICENSE
Requires-Dist: django ~=4.1
